LOGSAPI/Dataset.py
LOGSAPI/DatasetPage.py
LOGSAPI/Instrument.py
LOGSAPI/LOGSAPI.py
LOGSAPI/Sample.py
LOGSAPI/Track.py
LOGSAPI/__init__.py
logs_python_client-0.1.1b0.dist-info/METADATA
logs_python_client-0.1.1b0.dist-info/WHEEL
logs_python_client-0.1.1b0.dist-info/top_level.txt
logs_python_client-0.1.1b0.dist-info/RECORD
